dingtalk_api/__init__.py
dingtalk_api/client/__init__.py
dingtalk_api/client/contact/__init__.py
dingtalk_api/client/contact/user.py
dingtalk_api/client/im/__init__.py
dingtalk_api/client/im/robot.py
dingtalk_api/common/__init__.py
dingtalk_api/common/exception.py
dingtalk_api/common/response.py
dingtalk_api/core/__init__.py
dingtalk_api/core/auth.py
dingtalk_api/core/constant.py
dingtalk_api/core/session.py
dingtalk_api-0.0.4.dist-info/LICENSE
dingtalk_api-0.0.4.dist-info/METADATA
dingtalk_api-0.0.4.dist-info/WHEEL
dingtalk_api-0.0.4.dist-info/top_level.txt
dingtalk_api-0.0.4.dist-info/RECORD
