Metadata-Version: 2.1
Name: dingtalk-api
Version: 0.0.4
Summary: 钉钉服务端 API
Home-page: https://github.com/maxoyed/dingtalk-api
Author: maxoyed
Author-email: maxoyed@gmail.com
Classifier: Programming Language :: Python :: 3
Classifier: License :: OSI Approved :: MIT License
Classifier: Operating System :: OS Independent
Requires-Python: >=3.7
License-File: LICENSE
Requires-Dist: requests
